Adders/Full Adder/fadd.v
module fadd (in1,in2,cin,sum,cout);
  input in1,in2;
  input cin;
  output sum;
  output cout;
  
  assign {cout, sum} = in1 + in2 + cin;
endmodule

Adders/Full Adder/fadd4.v
`include "fadd.v"

module fadd4(in1,in2,cin,sum,cout);
  input[3:0] in1,in2;
  input cin;
  output[3:0] sum;
  output cout;
  wire[2:0] temp_cout;

  fadd af(.in1(in1[0]),.in2(in2[0]),.cin(cin),.sum(sum[0]),.cout(temp_cout[0]));
  fadd a(.in1(in1[1]),.in2(in2[1]),.cin(temp_cout[0]),.sum(sum[1]),.cout(temp_cout[1]));
  fadd b(.in1(in1[2]),.in2(in2[2]),.cin(temp_cout[1]),.sum(sum[2]),.cout(temp_cout[2]));
  fadd c(.in1(in1[3]),.in2(in2[3]),.cin(temp_cout[2]),.sum(sum[3]),.cout(cout));

endmodule

Adders/Full Adder/fadd_tb.v
`include "fadd4.v"

module newfadd4_test;

  reg[3:0] in1,in2;
  reg cin;
  wire cout;
  wire [3:0]sum; 
  reg[3:0] expected;
  integer i,j,k;
 
  fadd4 test_bench(in1,in2,cin,sum,cout);
  //fadd4 test_bench(.in1(in1),.in2(in2),.cin(cin),.sum(sum),.cout(cout));
 
  initial 
    begin
      
     for(k=0; k<2; k=k+1)
      begin
       cin =k;
       
       for(i=0; i<16; i=i+1)
        begin
         in1 = i;
      
         for(j=0; j<16; j=j+1)
           begin
            in2 = j;
            
            #5
            expected = in1+in2+cin;
            if(sum[3:0] == expected[3:0]) //&& cout == expected[4])
              begin
              $display("Test successfull");
              //$display($time," ns monitor in1= %b,in2= %b,cin= %b,sum = %b,cout= %b,expected=%d",in1,in2,cin,sum,cout,expected);
              end
            else
              begin
              $display("Test Fail");
              //$display($time,"ns Test Faill in1= %b,in2= %b,cin= %b,sum = %b,cout= %b, expected=%d",in1,in2,cin,sum,cout,expected);
              
              end
           end
        end
      end
        
  end

  initial
    $monitor($time," ns monitor in1= %b,in2= %b,cin= %b,sum = %b,cout= %b,expected=%d",in1,in2,cin,sum,cout,expected);

initial 
   begin
     $dumpfile("test_fadd.vcd");
     $dumpvars;
     #500 $finish;
   end

endmodule

Adders/Full Adder/test_fadd.vcd
$date
	Thu Dec 02 02:05:28 2021
$end
$version
	Icarus Verilog
$end
$timescale
	1s
$end
$scope module newfadd4_test $end
$var wire 4 ! sum [3:0] $end
$var wire 1 " cout $end
$var reg 1 # cin $end
$var reg 4 $ expected [3:0] $end
$var reg 4 % in1 [3:0] $end
$var reg 4 & in2 [3:0] $end
$var integer 32 ' i [31:0] $end
$var integer 32 ( j [31:0] $end
$var integer 32 ) k [31:0] $end
$scope module test_bench $end
$var wire 1 # cin $end
$var wire 4 * in1 [3:0] $end
$var wire 4 + in2 [3:0] $end
$var wire 3 , temp_cout [2:0] $end
$var wire 4 - sum [3:0] $end
$var wire 1 " cout $end
$scope module a $end
$var wire 1 . cin $end
$var wire 1 / in1 $end
$var wire 1 0 in2 $end
$var wire 1 1 sum $end
$var wire 1 2 cout $end
$upscope $end
$scope module af $end
$var wire 1 # cin $end
$var wire 1 3 in1 $end
$var wire 1 4 in2 $end
$var wire 1 5 sum $end
$var wire 1 6 cout $end
$upscope $end
$scope module b $end
$var wire 1 7 cin $end
$var wire 1 8 in1 $end
$var wire 1 9 in2 $end
$var wire 1 : sum $end
$var wire 1 ; cout $end
$upscope $end
$scope module c $end
$var wire 1 < cin $end
$var wire 1 = in1 $end
$var wire 1 > in2 $end
$var wire 1 ? sum $end
$var wire 1 " cout $end
$upscope $end
$upscope $end
$upscope $end
$enddefinitions $end
#0
$dumpvars
0?
0>
0=
0<
0;
0:
09
08
07
06
05
04
03
02
01
00
0/
0.
b0 -
b0 ,
b0 +
b0 *
b0 )
b0 (
b0 '
b0 &
b0 %
bx $
0#
0"
b0 !
$end
#5
b1 !
b1 -
15
14
b1 &
b1 +
b1 (
b0 $
#10
05
b10 !
b10 -
11
04
10
b10 &
b10 +
b10 (
b1 $
#15
b11 !
b11 -
15
14
b11 &
b11 +
b11 (
b10 $
#20
05
01
b100 !
b100 -
1:
04
00
19
b100 &
b100 +
b100 (
b11 $
#25
b101 !
b101 -
15
14
b101 &
b101 +
b101 (
b100 $
#30
05
b110 !
b110 -
11
04
10
b110 &
b110 +
b110 (
b101 $
#35
b111 !
b111 -
15
14
b111 &
b111 +
b111 (
b110 $
#40
05
01
0:
b1000 !
b1000 -
1?
04
00
09
1>
b1000 &
b1000 +
b1000 (
b111 $
#45
b1001 !
b1001 -
15
14
b1001 &
b1001 +
b1001 (
b1000 $
#50
05
b1010 !
b1010 -
11
04
10
b1010 &
b1010 +
b1010 (
b1001 $
#55
b1011 !
b1011 -
15
14
b1011 &
b1011 +
b1011 (
b1010 $
#60
05
01
b1100 !
b1100 -
1:
04
00
19
b1100 &
b1100 +
b1100 (
b1011 $
#65
b1101 !
b1101 -
15
14
b1101 &
b1101 +
b1101 (
b1100 $
#70
05
b1110 !
b1110 -
11
04
10
b1110 &
b1110 +
b1110 (
b1101 $
#75
b1111 !
b1111 -
15
14
b1111 &
b1111 +
b1111 (
b1110 $
#80
01
0:
b1 !
b1 -
0?
04
00
09
0>
13
b0 &
b0 +
b1 %
b1 *
b1 '
b0 (
b1111 $
#85
11
1.
b10 !
b10 -
05
b1 ,
16
14
b1 &
b1 +
b1 (
b1 $
#90
0:
0.
07
15
06
b11 !
b11 -
11
b0 ,
02
04
10
b10 &
b10 +
b10 (
b10 $
#95
1:
17
01
12
1.
b100 !
b100 -
05
b11 ,
16
14
b11 &
b11 +
b11 (
b11 $
#100
0?
0.
07
0<
15
06
01
02
b101 !
b101 -
1:
b0 ,
0;
04
00
19
b100 &
b100 +
b100 (
b100 $
#105
11
1.
b110 !
b110 -
05
b1 ,
16
14
b101 &
b101 +
b101 (
b101 $
#110
0?
0<
1:
0;
0.
07
15
06
b111 !
b111 -
11
b0 ,
02
04
10
b110 &
b110 +
b110 (
b110 $
#115
1?
1<
0:
1;
17
01
12
1.
b1000 !
b1000 -
05
b111 ,
16
14
b111 &
b111 +
b111 (
b111 $
#120
0.
07
0<
15
06
01
02
0:
b0 ,
0;
b1001 !
b1001 -
1?
0"
04
00
09
1>
b1000 &
b1000 +
b1000 (
b1000 $
#125
11
1.
b1010 !
b1010 -
05
b1 ,
16
14
b1001 &
b1001 +
b1001 (
b1001 $
#130
0:
0.
07
15
06
b1011 !
b1011 -
11
b0 ,
02
04
10
b1010 &
b1010 +
b1010 (
b1010 $
#135
1:
17
01
12
1.
b1100 !
b1100 -
05
b11 ,
16
14
b1011 &
b1011 +
b1011 (
b1011 $
#140
1?
0"
0.
07
0<
15
06
01
02
b1101 !
b1101 -
1:
b0 ,
0;
04
00
19
b1100 &
b1100 +
b1100 (
b1100 $
#145
11
1.
b1110 !
b1110 -
05
b1 ,
16
14
b1101 &
b1101 +
b1101 (
b1101 $
#150
1?
0"
0<
1:
0;
0.
07
15
06
b1111 !
b1111 -
11
b0 ,
02
04
10
b1110 &
b1110 +
b1110 (
b1110 $
#155
0?
1"
1<
0:
1;
17
01
12
1.
b0 !
b0 -
05
b111 ,
16
14
b1111 &
b1111 +
b1111 (
b1111 $
#160
07
11
02
0<
0.
0:
0;
b10 !
b10 -
0?
0"
b0 ,
06
04
00
09
0>
03
1/
b0 &
b0 +
b10 %
b10 *
b10 '
b0 (
b0 $
#165
b11 !
b11 -
15
14
b1 &
b1 +
b1 (
b10 $
#170
1:
17
05
b100 !
b100 -
01
b10 ,
12
04
10
b10 &
b10 +
b10 (
b11 $
#175
b101 !
b101 -
15
14
b11 &
b11 +
b11 (
b100 $
#180
0?
07
0<
05
11
02
b110 !
b110 -
1:
b0 ,
0;
04
00
19
b100 &
b100 +
b100 (
b101 $
#185
b111 !
b111 -
15
14
b101 &
b101 +
b101 (
b110 $
#190
1?
1<
0:
1;
17
05
b1000 !
b1000 -
01
b110 ,
12
04
10
b110 &
b110 +
b110 (
b111 $
#195
b1001 !
b1001 -
15
14
b111 &
b111 +
b111 (
b1000 $
#200
07
0<
05
11
02
0:
b0 ,
0;
b1010 !
b1010 -
1?
0"
04
00
09
1>
b1000 &
b1000 +
b1000 (
b1001 $
#205
b1011 !
b1011 -
15
14
b1001 &
b1001 +
b1001 (
b1010 $
#210
1:
17
05
b1100 !
b1100 -
01
b10 ,
12
04
10
b1010 &
b1010 +
b1010 (
b1011 $
#215
b1101 !
b1101 -
15
14
b1011 &
b1011 +
b1011 (
b1100 $
#220
1?
0"
07
0<
05
11
02
b1110 !
b1110 -
1:
b0 ,
0;
04
00
19
b1100 &
b1100 +
b1100 (
b1101 $
#225
b1111 !
b1111 -
15
14
b1101 &
b1101 +
b1101 (
b1110 $
#230
0?
1"
1<
0:
1;
17
05
b0 !
b0 -
01
b110 ,
12
04
10
b1110 &
b1110 +
b1110 (
b1111 $
#235
b1 !
b1 -
15
14
b1111 &
b1111 +
b1111 (
b0 $
#240
07
0<
11
02
0:
b0 ,
0;
b11 !
b11 -
0?
0"
04
00
09
0>
13
b0 &
b0 +
b11 %
b11 *
b11 '
b0 (
b1 $
#245
1:
17
01
12
1.
b100 !
b100 -
05
b11 ,
16
14
b1 &
b1 +
b1 (
b11 $
#250
0.
15
b10 ,
06
b101 !
b101 -
01
04
10
b10 &
b10 +
b10 (
b100 $
#255
11
1.
b110 !
b110 -
05
b11 ,
16
14
b11 &
b11 +
b11 (
b101 $
#260
07
02
0?
0.
0<
15
06
11
b111 !
b111 -
1:
b0 ,
0;
04
00
19
b100 &
b100 +
b100 (
b110 $
#265
1?
1<
0:
1;
17
01
12
1.
b1000 !
b1000 -
05
b111 ,
16
14
b101 &
b101 +
b101 (
b111 $
#270
0.
15
b110 ,
06
b1001 !
b1001 -
01
04
10
b110 &
b110 +
b110 (
b1000 $
#275
11
1.
b1010 !
b1010 -
05
b111 ,
16
14
b111 &
b111 +
b111 (
b1001 $
#280
07
02
0.
0<
15
06
11
0:
b0 ,
0;
b1011 !
b1011 -
1?
0"
04
00
09
1>
b1000 &
b1000 +
b1000 (
b1010 $
#285
1:
17
01
12
1.
b1100 !
b1100 -
05
b11 ,
16
14
b1001 &
b1001 +
b1001 (
b1011 $
#290
0.
15
b10 ,
06
b1101 !
b1101 -
01
04
10
b1010 &
b1010 +
b1010 (
b1100 $
#295
11
1.
b1110 !
b1110 -
05
b11 ,
16
14
b1011 &
b1011 +
b1011 (
b1101 $
#300
07
02
1?
0"
0.
0<
15
06
11
b1111 !
b1111 -
1:
b0 ,
0;
04
00
19
b1100 &
b1100 +
b1100 (
b1110 $
#305
0?
1"
1<
0:
1;
17
01
12
1.
b0 !
b0 -
05
b111 ,
16
14
b1101 &
b1101 +
b1101 (
b1111 $
#310
0.
15
b110 ,
06
b1 !
b1 -
01
04
10
b1110 &
b1110 +
b1110 (
b0 $
#315
11
1.
b10 !
b10 -
05
b111 ,
16
14
b1111 &
b1111 +
b1111 (
b1 $
#320
0<
1:
0;
01
07
0.
02
b100 !
b100 -
0?
0"
b0 ,
06
04
00
09
0>
03
0/
18
b0 &
b0 +
b100 %
b100 *
b100 '
b0 (
b10 $
#325
b101 !
b101 -
15
14
b1 &
b1 +
b1 (
b100 $
#330
05
b110 !
b110 -
11
04
10
b10 &
b10 +
b10 (
b101 $
#335
b111 !
b111 -
15
14
b11 &
b11 +
b11 (
b110 $
#340
1?
1<
05
01
b1000 !
b1000 -
0:
b100 ,
1;
04
00
19
b100 &
b100 +
b100 (
b111 $
#345
b1001 !
b1001 -
15
14
b101 &
b101 +
b101 (
b1000 $
#350
05
b1010 !
b1010 -
11
04
10
b110 &
b110 +
b110 (
b1001 $
#355
b1011 !
b1011 -
15
14
b111 &
b111 +
b111 (
b1010 $
#360
0<
05
01
1:
b0 ,
0;
b1100 !
b1100 -
1?
0"
04
00
09
1>
b1000 &
b1000 +
b1000 (
b1011 $
#365
b1101 !
b1101 -
15
14
b1001 &
b1001 +
b1001 (
b1100 $
#370
05
b1110 !
b1110 -
11
04
10
b1010 &
b1010 +
b1010 (
b1101 $
#375
b1111 !
b1111 -
15
14
b1011 &
b1011 +
b1011 (
b1110 $
#380
0?
1"
1<
05
01
b0 !
b0 -
0:
b100 ,
1;
04
00
19
b1100 &
b1100 +
b1100 (
b1111 $
#385
b1 !
b1 -
15
14
b1101 &
b1101 +
b1101 (
b0 $
#390
05
b10 !
b10 -
11
04
10
b1110 &
b1110 +
b1110 (
b1 $
#395
b11 !
b11 -
15
14
b1111 &
b1111 +
b1111 (
b10 $
#400
0<
01
1:
b0 ,
0;
b101 !
b101 -
0?
0"
04
00
09
0>
13
b0 &
b0 +
b101 %
b101 *
b101 '
b0 (
b11 $
#405
11
1.
b110 !
b110 -
05
b1 ,
16
14
b1 &
b1 +
b1 (
b101 $
#410
0?
0<
1:
0;
0.
07
15
06
b111 !
b111 -
11
b0 ,
02
04
10
b10 &
b10 +
b10 (
b110 $
#415
1?
1<
0:
1;
17
01
12
1.
b1000 !
b1000 -
05
b111 ,
16
14
b11 &
b11 +
b11 (
b111 $
#420
0.
07
15
06
01
b100 ,
02
b1001 !
b1001 -
0:
04
00
19
b100 &
b100 +
b100 (
b1000 $
#425
11
1.
b1010 !
b1010 -
05
b101 ,
16
14
b101 &
b101 +
b101 (
b1001 $
#430
0:
0.
07
15
06
b1011 !
b1011 -
11
b100 ,
02
04
10
b110 &
b110 +
b110 (
b1010 $
#435
1:
17
01
12
1.
b1100 !
b1100 -
05
b111 ,
16
14
b111 &
b111 +
b111 (
b1011 $
#440
0<
0;
0.
07
15
06
01
b0 ,
02
1:
b1101 !
b1101 -
1?
0"
04
00
09
1>
b1000 &
b1000 +
b1000 (
b1100 $
#445
11
1.
b1110 !
b1110 -
05
b1 ,
16
14
b1001 &
b1001 +
b1001 (
b1101 $
#450
1?
0"
0<
1:
0;
0.
07
15
06
b1111 !
b1111 -
11
b0 ,
02
04
10
b1010 &
b1010 +
b1010 (
b1110 $
#455
0?
1"
1<
0:
1;
17
01
12
1.
b0 !
b0 -
05
b111 ,
16
14
b1011 &
b1011 +
b1011 (
b1111 $
#460
0.
07
15
06
01
b100 ,
02
b1 !
b1 -
0:
04
00
19
b1100 &
b1100 +
b1100 (
b0 $
#465
11
1.
b10 !
b10 -
05
b101 ,
16
14
b1101 &
b1101 +
b1101 (
b1 $
#470
0:
0.
07
15
06
b11 !
b11 -
11
b100 ,
02
04
10
b1110 &
b1110 +
b1110 (
b10 $
#475
1:
17
01
12
1.
b100 !
b100 -
05
b111 ,
16
14
b1111 &
b1111 +
b1111 (
b11 $
#480
0<
0;
07
11
02
0.
1:
b110 !
b110 -
0?
0"
b0 ,
06
04
00
09
0>
03
1/
b0 &
b0 +
b110 %
b110 *
b110 '
b0 (
b100 $
#485
b111 !
b111 -
15
14
b1 &
b1 +
b1 (
b110 $
#490
1?
1<
0:
1;
17
05
b1000 !
b1000 -
01
b110 ,
12
04
10
b10 &
b10 +
b10 (
b111 $
#495
b1001 !
b1001 -
15
14
b11 &
b11 +
b11 (
b1000 $
#500
b1001 $
