Shift Register/Bidirectional Shift Register/Bidirectional_Shift_Register.v
module Bidirect_shift(q,clk,shift,load,in);

   output reg [3:0] q;
   input [3:0] in;
   input clk;
   input shift,load;

   always @(posedge clk,shift,load,in) begin
       
       if (load)
         q=in;

       else begin
         
         if(shift) 
           q = q << 1;         

         else 
           q = q >> 1;
           
       end
       
   end

   endmodule

Shift Register/Bidirectional Shift Register/testb_bidirectional_shift.v
`include "Bidirectional_Shift_Register.v"

module testb_bidirectional_shift;

   wire [3:0] q;
   reg [3:0] in;
   reg clk;
   reg shift,load;

   Bidirect_shift shift1 (q,clk,shift,load,in);

   initial begin
     clk = 1'b0;
     shift = 1'b0;
     load = 1'b1;
   end

   always begin
       #1 clk = ~clk;
   end

   initial begin
        in =4'b1010;
       #1 load = 1'b0;
        
       #5 shift = 1'b1;

       #5 load =1'b1;
          in = 4'b0100;
          shift = 1'b0;
          load = 1'b0;
   end


   initial begin
       $monitor($time,"ns clk=%b,load=%b,shift=%b,in=%b,q=%b",clk,load,shift,in,q);
       $dumpfile("testb_bidirectional_shift.vcd");
       $dumpvars;
       #50 $finish;
   end
   endmodule

Shift Register/Bidirectional Shift Register/testb_bidirectional_shift.vcd
$date
	Sat Nov 20 13:54:28 2021
$end
$version
	Icarus Verilog
$end
$timescale
	1s
$end
$scope module testb_bidirectional_shift $end
$var wire 4 ! q [3:0] $end
$var reg 1 " clk $end
$var reg 4 # in [3:0] $end
$var reg 1 $ load $end
$var reg 1 % shift $end
$scope module shift1 $end
$var wire 1 " clk $end
$var wire 4 & in [3:0] $end
$var wire 1 $ load $end
$var wire 1 % shift $end
$var reg 4 ' q [3:0] $end
$upscope $end
$upscope $end
$enddefinitions $end
#0
$dumpvars
b1010 '
b1010 &
0%
1$
b1010 #
0"
b1010 !
$end
#1
b101 !
b101 '
0$
1"
#2
0"
#3
b10 !
b10 '
1"
#4
0"
#5
b1 !
b1 '
1"
#6
b10 !
b10 '
0"
1%
#7
b100 !
b100 '
1"
#8
0"
#9
b1000 !
b1000 '
1"
#10
0"
#11
b100 !
b100 '
1"
0%
b100 #
b100 &
0$
#12
0"
#13
b10 !
b10 '
1"
#14
0"
#15
b1 !
b1 '
1"
#16
0"
#17
b0 !
b0 '
1"
