Flip Flops/JK Flip_Flop/JK using D Flip_Flop/Dflip_flop.v
module dff(q,qbar,clk,d);

output reg q;
output reg qbar;
input clk;
input d;

always @(posedge clk ) begin
    q = d;
    qbar = ~d;
end

endmodule

Flip Flops/JK Flip_Flop/JK using D Flip_Flop/jk_ff.v
`include "Dflip_flop.v"

module jk_ff(q,qbar,clk,j,k);

   output q;
   output qbar;
   input clk;
   input j,k;
   wire [3:0] w;

   /*initial begin
       q=1'b0;
       qbar = 1'b1;
   end */

   not g1 (w[0],k);
   
   and g2 (w[1],q,w[0]);
   and g3 (w[2],qbar,j);

   or g4 (w[3],w[2],w[1]);

   dff dff1(q,qbar,clk,w[3]);

endmodule

Flip Flops/JK Flip_Flop/JK using D Flip_Flop/testb_jkff.v
`include "jk_ff.v"

module testb_dff;

  wire q,qbar;
  reg clk,j,k;
  
  jk_ff ff1 (q,qbar,clk,j,k);

  initial
    clk = 1'b0;

  always
    #1 clk = ~clk;

  initial begin

    #5 j=1'b0;
       k=1'b1;

    #3 j=1'b0;
       k=1'b0;

    #10 j=1'b1;
        k=1'b0;

    #10 j=1'b1;
        k=1'b1;
  end

  initial begin
       $monitor($time,"ns clk=%b,j=%b,k=%b,q=%b,qbar=%b",clk,j,k,q,qbar);
       $dumpfile("testb_jkff.vcd");
       $dumpvars;
       #50 $finish;
   end
endmodule

Flip Flops/JK Flip_Flop/JK using D Flip_Flop/testb_jkff.vcd
$date
	Sat Nov 20 21:17:11 2021
$end
$version
	Icarus Verilog
$end
$timescale
	1s
$end
$scope module testb_dff $end
$var wire 1 ! qbar $end
$var wire 1 " q $end
$var reg 1 # clk $end
$var reg 1 $ j $end
$var reg 1 % k $end
$scope module ff1 $end
$var wire 1 # clk $end
$var wire 1 $ j $end
$var wire 1 % k $end
$var wire 4 & w [3:0] $end
$var wire 1 ! qbar $end
$var wire 1 " q $end
$scope module dff1 $end
$var wire 1 # clk $end
$var wire 1 ' d $end
$var reg 1 " q $end
$var reg 1 ! qbar $end
$upscope $end
$upscope $end
$upscope $end
$enddefinitions $end
#0
$dumpvars
x'
bx &
x%
x$
0#
x"
x!
$end
#1
1#
#2
0#
#3
1#
#4
0#
#5
0'
b0 &
1#
1%
0$
#6
0#
#7
1!
0"
1#
#8
b1 &
0#
0%
#9
1#
#10
0#
#11
1#
#12
0#
#13
1#
#14
0#
#15
1#
#16
0#
#17
1#
#18
1'
b1101 &
0#
1$
#19
b1011 &
0!
1"
1#
#20
0#
#21
1#
#22
0#
#23
1#
#24
0#
#25
1#
#26
0#
#27
1#
#28
0'
b0 &
0#
1%
#29
1'
b1100 &
1!
0"
1#
#30
0#
#31
0'
b0 &
0!
1"
1#
#32
0#
#33
1'
b1100 &
1!
0"
1#
#34
0#
#35
0'
b0 &
0!
1"
1#
#36
0#
#37
1'
b1100 &
1!
0"
1#
#38
0#
#39
0'
b0 &
0!
1"
1#
#40
0#
#41
1'
b1100 &
1!
0"
1#
#42
0#
#43
0'
b0 &
0!
1"
1#
#44
0#
#45
1'
b1100 &
1!
0"
1#
#46
0#
#47
0'
b0 &
0!
1"
1#
#48
0#
#49
1'
b1100 &
1!
0"
1#
