Counters/Asynchronous counters/Ripple Counter/Ripple_jk/jkff.v
module jkff(q,qbar,clk,clr,enable,j,k);

   output reg q;
   output reg qbar;
   input clk;
   input j,k;
   input clr,enable;

   always @(posedge clk,j,k,clr,enable) begin

       if(enable) begin
         
         if(clr) begin
           q=1'b0;
           qbar=1'b1;
         end
        
        else begin

          case ({j,k})
          2'b00 : begin q <=q; qbar <= qbar; end
          2'b01 : begin q <=0; qbar <= 1; end
          2'b10 : begin q <=1; qbar <= 0; end
          2'b11 : begin q <=qbar; qbar <= q; end 
         endcase
         
        end

       end    
   end
endmodule

Counters/Asynchronous counters/Ripple Counter/Ripple_jk/ripple_counter.v
`include "jkff.v"

module ripple_counter(q,clk,clr,enable);

    output [2:0] q;
    input clk;
    input clr,enable;

    //jk_ff ff0 (.q(q[0]),.clk(clk),.j(1'b1),.k(1'b0));
    jkff ff1 (.q(q[0]),.clr(clr),.enable(enable),.clk(clk),.j(1'b1),.k(1'b1));
    jkff ff2 (.q(q[1]),.clr(clr),.enable(enable),.clk(q[0]),.j(1'b1),.k(1'b1));
    jkff ff3 (.q(q[2]),.clr(clr),.enable(enable),.clk(q[1]),.j(1'b1),.k(1'b1));

endmodule

Counters/Asynchronous counters/Ripple Counter/Ripple_jk/testb_ripple_counter.v
`include "ripple_counter.v"

module testb_ripple_counter;

    wire [2:0] q;
    reg clk;
    reg clr,enable;

   ripple_counter count1 (.q(q),.clr(clr),.enable(enable),.clk(clk));

    initial begin
        clk = 1'b0;
        clr =1'b1;
        enable=1'b1;
       #5 clr =1'b0;
        #50 $finish;
    end

    always
       #1 clk = ~clk;

    initial begin
       $monitor($time,"ns clk=%b,clr=%b,enable=%b,q=%b",clk,clr,enable,q);
       $dumpfile("testb_ripple_counter.vcd");
       $dumpvars;
    end

endmodule

Counters/Asynchronous counters/Ripple Counter/Ripple_jk/testb_ripple_counter.vcd
$date
	Sun Dec 05 12:08:58 2021
$end
$version
	Icarus Verilog
$end
$timescale
	1s
$end
$scope module testb_ripple_counter $end
$var wire 3 ! q [2:0] $end
$var reg 1 " clk $end
$var reg 1 # clr $end
$var reg 1 $ enable $end
$scope module count1 $end
$var wire 1 " clk $end
$var wire 1 # clr $end
$var wire 1 $ enable $end
$var wire 3 % q [2:0] $end
$scope module ff1 $end
$var wire 1 " clk $end
$var wire 1 # clr $end
$var wire 1 $ enable $end
$var wire 1 & j $end
$var wire 1 ' k $end
$var reg 1 ( q $end
$var reg 1 ) qbar $end
$upscope $end
$scope module ff2 $end
$var wire 1 * clk $end
$var wire 1 # clr $end
$var wire 1 $ enable $end
$var wire 1 + j $end
$var wire 1 , k $end
$var reg 1 - q $end
$var reg 1 . qbar $end
$upscope $end
$scope module ff3 $end
$var wire 1 / clk $end
$var wire 1 # clr $end
$var wire 1 $ enable $end
$var wire 1 0 j $end
$var wire 1 1 k $end
$var reg 1 2 q $end
$var reg 1 3 qbar $end
$upscope $end
$upscope $end
$upscope $end
$enddefinitions $end
#0
$dumpvars
13
02
11
10
0/
1.
0-
1,
1+
0*
1)
0(
1'
1&
b0 %
1$
1#
0"
b0 !
$end
#1
1"
#2
0"
#3
1"
#4
0"
#5
1*
0/
0)
1(
1.
0-
13
b1 !
b1 %
02
1"
0#
#6
0"
#7
0*
1)
b0 !
b0 %
0(
1"
#8
0"
#9
03
12
1/
0.
1-
1*
0)
b111 !
b111 %
1(
1"
#10
0"
#11
0*
1)
b110 !
b110 %
0(
1"
#12
0"
#13
0/
1.
0-
1*
0)
b101 !
b101 %
1(
1"
#14
0"
#15
0*
1)
b100 !
b100 %
0(
1"
#16
0"
#17
13
02
1/
0.
1-
1*
0)
b11 !
b11 %
1(
1"
#18
0"
#19
0*
1)
b10 !
b10 %
0(
1"
#20
0"
#21
0/
1.
0-
1*
0)
b1 !
b1 %
1(
1"
#22
0"
#23
0*
1)
b0 !
b0 %
0(
1"
#24
0"
#25
03
12
1/
0.
1-
1*
0)
b111 !
b111 %
1(
1"
#26
0"
#27
0*
1)
b110 !
b110 %
0(
1"
#28
0"
#29
0/
1.
0-
1*
0)
b101 !
b101 %
1(
1"
#30
0"
#31
0*
1)
b100 !
b100 %
0(
1"
#32
0"
#33
13
02
1/
0.
1-
1*
0)
b11 !
b11 %
1(
1"
#34
0"
#35
0*
1)
b10 !
b10 %
0(
1"
#36
0"
#37
0/
1.
0-
1*
0)
b1 !
b1 %
1(
1"
#38
0"
#39
0*
1)
b0 !
b0 %
0(
1"
#40
0"
#41
03
12
1/
0.
1-
1*
0)
b111 !
b111 %
1(
1"
#42
0"
#43
0*
1)
b110 !
b110 %
0(
1"
#44
0"
#45
0/
1.
0-
1*
0)
b101 !
b101 %
1(
1"
#46
0"
#47
0*
1)
b100 !
b100 %
0(
1"
#48
0"
#49
13
02
1/
0.
1-
1*
0)
b11 !
b11 %
1(
1"
#50
0"
#51
0*
1)
b10 !
b10 %
0(
1"
#52
0"
#53
0/
1.
0-
1*
0)
b1 !
b1 %
1(
1"
#54
0"
#55
0*
1)
b0 !
b0 %
0(
1"
